[{"full": "休診", "name": "林德宇", "hospital": "ndmctsgh - 內湖院區", "outpatient": "感染及熱帶醫學科", "dept": "內科", "link": "NA", "time": "morning", "date": "20150729", "crawlTime": "20150729 23:10"},
{"full": "25 ", "name": "張峰義", "hospital": "ndmctsgh - 內湖院區", "outpatient": "感染及熱帶醫學科", "dept": "內科", "link": "NA", "time": "morning", "date": "20150730", "crawlTime": "20150729 23:10"},
{"full": "42 ", "name": "林永崇", "hospital": "ndmctsgh - 內湖院區", "outpatient": "感染及熱帶醫學科", "dept": "內科", "link": "NA", "time": "morning", "date": "20150730", "crawlTime": "20150729 23:10"},
{"full": "請現場掛", "name": "王甯祺", "hospital": "ndmctsgh - 內湖院區", "outpatient": "感染及熱帶醫學科", "dept": "內科", "link": "NA", "time": "morning", "date": "20150731", "crawlTime": "20150729 23:10"},
{"full": "28 ", "name": "王甯祺", "hospital": "ndmctsgh - 內湖院區", "outpatient": "感染及熱帶醫學科", "dept": "內科", "link": "NA", "time": "morning", "date": "20150803", "crawlTime": "20150729 23:11"},
{"full": "3 ", "name": "王甯祺", "hospital": "ndmctsgh - 內湖院區", "outpatient": "感染及熱帶醫學科", "dept": "內科", "link": "NA", "time": "morning", "date": "20150804", "crawlTime": "20150729 23:11"},
{"full": "6 ", "name": "邱勝康", "hospital": "ndmctsgh - 內湖院區", "outpatient": "感染及熱帶醫學科", "dept": "內科", "link": "NA", "time": "morning", "date": "20150804", "crawlTime": "20150729 23:11"},
{"full": "請現場掛", "name": "葉國明", "hospital": "ndmctsgh - 內湖院區", "outpatient": "感染及熱帶醫學科", "dept": "內科", "link": "NA", "time": "afternoon", "date": "20150729", "crawlTime": "20150729 23:11"},
{"full": "請現場掛", "name": "林永崇", "hospital": "ndmctsgh - 內湖院區", "outpatient": "感染及熱帶醫學科", "dept": "內科", "link": "NA", "time": "afternoon", "date": "20150729", "crawlTime": "20150729 23:11"},
{"full": "14 ", "name": "葉國明", "hospital": "ndmctsgh - 內湖院區", "outpatient": "感染及熱帶醫學科", "dept": "內科", "link": "NA", "time": "afternoon", "date": "20150730", "crawlTime": "20150729 23:12"},
{"full": "43 ", "name": "王甯祺", "hospital": "ndmctsgh - 內湖院區", "outpatient": "感染及熱帶醫學科", "dept": "內科", "link": "NA", "time": "afternoon", "date": "20150730", "crawlTime": "20150729 23:12"},
{"full": "請現場掛", "name": "楊雅頌", "hospital": "ndmctsgh - 內湖院區", "outpatient": "感染及熱帶醫學科", "dept": "內科", "link": "NA", "time": "afternoon", "date": "20150731", "crawlTime": "20150729 23:12"},
{"full": "33 ", "name": "林德宇", "hospital": "ndmctsgh - 內湖院區", "outpatient": "感染及熱帶醫學科", "dept": "內科", "link": "NA", "time": "afternoon", "date": "20150731", "crawlTime": "20150729 23:13"},
{"full": "13 ", "name": "邱勝康", "hospital": "ndmctsgh - 內湖院區", "outpatient": "感染及熱帶醫學科", "dept": "內科", "link": "NA", "time": "afternoon", "date": "20150803", "crawlTime": "20150729 23:13"},
{"full": "19 ", "name": "張峰義", "hospital": "ndmctsgh - 內湖院區", "outpatient": "感染及熱帶醫學科", "dept": "內科", "link": "NA", "time": "afternoon", "date": "20150803", "crawlTime": "20150729 23:13"},
{"full": "13 ", "name": "葉國明", "hospital": "ndmctsgh - 內湖院區", "outpatient": "感染及熱帶醫學科", "dept": "內科", "link": "NA", "time": "afternoon", "date": "20150804", "crawlTime": "20150729 23:13"},
{"full": "21 ", "name": "林德宇", "hospital": "ndmctsgh - 內湖院區", "outpatient": "感染及熱帶醫學科", "dept": "內科", "link": "NA", "time": "afternoon", "date": "20150804", "crawlTime": "20150729 23:14"},
{"full": "請現場掛", "name": "葉國明", "hospital": "ndmctsgh - 內湖院區", "outpatient": "感染及熱帶醫學科", "dept": "內科", "link": "NA", "time": "night", "date": "20150729", "crawlTime": "20150729 23:14"},
{"full": "9 ", "name": "林德宇", "hospital": "ndmctsgh - 內湖院區", "outpatient": "感染及熱帶醫學科", "dept": "內科", "link": "NA", "time": "morning", "date": "20150805", "crawlTime": "20150729 23:14"},
{"full": "13 ", "name": "張峰義", "hospital": "ndmctsgh - 內湖院區", "outpatient": "感染及熱帶醫學科", "dept": "內科", "link": "NA", "time": "morning", "date": "20150806", "crawlTime": "20150729 23:14"},
{"full": "25 ", "name": "林永崇", "hospital": "ndmctsgh - 內湖院區", "outpatient": "感染及熱帶醫學科", "dept": "內科", "link": "NA", "time": "morning", "date": "20150806", "crawlTime": "20150729 23:15"},
{"full": "請現場掛", "name": "王甯祺", "hospital": "ndmctsgh - 內湖院區", "outpatient": "感染及熱帶醫學科", "dept": "內科", "link": "NA", "time": "morning", "date": "20150807", "crawlTime": "20150729 23:15"},
{"full": "19 ", "name": "王甯祺", "hospital": "ndmctsgh - 內湖院區", "outpatient": "感染及熱帶醫學科", "dept": "內科", "link": "NA", "time": "morning", "date": "20150810", "crawlTime": "20150729 23:15"},
{"full": "7 ", "name": "邱勝康", "hospital": "ndmctsgh - 內湖院區", "outpatient": "感染及熱帶醫學科", "dept": "內科", "link": "NA", "time": "morning", "date": "20150811", "crawlTime": "20150729 23:16"},
{"full": "7 ", "name": "葉國明", "hospital": "ndmctsgh - 內湖院區", "outpatient": "感染及熱帶醫學科", "dept": "內科", "link": "NA", "time": "afternoon", "date": "20150805", "crawlTime": "20150729 23:16"},
{"full": "29 ", "name": "林永崇", "hospital": "ndmctsgh - 內湖院區", "outpatient": "感染及熱帶醫學科", "dept": "內科", "link": "NA", "time": "afternoon", "date": "20150805", "crawlTime": "20150729 23:16"},
{"full": "7 ", "name": "葉國明", "hospital": "ndmctsgh - 內湖院區", "outpatient": "感染及熱帶醫學科", "dept": "內科", "link": "NA", "time": "afternoon", "date": "20150806", "crawlTime": "20150729 23:16"},
{"full": "28 ", "name": "王甯祺", "hospital": "ndmctsgh - 內湖院區", "outpatient": "感染及熱帶醫學科", "dept": "內科", "link": "NA", "time": "afternoon", "date": "20150806", "crawlTime": "20150729 23:17"},
{"full": "6 ", "name": "楊雅頌", "hospital": "ndmctsgh - 內湖院區", "outpatient": "感染及熱帶醫學科", "dept": "內科", "link": "NA", "time": "afternoon", "date": "20150807", "crawlTime": "20150729 23:17"},
{"full": "13 ", "name": "林德宇", "hospital": "ndmctsgh - 內湖院區", "outpatient": "感染及熱帶醫學科", "dept": "內科", "link": "NA", "time": "afternoon", "date": "20150807", "crawlTime": "20150729 23:17"},
{"full": "9 ", "name": "張峰義", "hospital": "ndmctsgh - 內湖院區", "outpatient": "感染及熱帶醫學科", "dept": "內科", "link": "NA", "time": "afternoon", "date": "20150810", "crawlTime": "20150729 23:18"},
{"full": "13 ", "name": "邱勝康", "hospital": "ndmctsgh - 內湖院區", "outpatient": "感染及熱帶醫學科", "dept": "內科", "link": "NA", "time": "afternoon", "date": "20150810", "crawlTime": "20150729 23:18"},
{"full": "9 ", "name": "葉國明", "hospital": "ndmctsgh - 內湖院區", "outpatient": "感染及熱帶醫學科", "dept": "內科", "link": "NA", "time": "afternoon", "date": "20150811", "crawlTime": "20150729 23:18"},
{"full": "15 ", "name": "林德宇", "hospital": "ndmctsgh - 內湖院區", "outpatient": "感染及熱帶醫學科", "dept": "內科", "link": "NA", "time": "afternoon", "date": "20150811", "crawlTime": "20150729 23:19"},
{"full": "6 ", "name": "葉國明", "hospital": "ndmctsgh - 內湖院區", "outpatient": "感染及熱帶醫學科", "dept": "內科", "link": "NA", "time": "night", "date": "20150805", "crawlTime": "20150729 23:19"},
{"full": "13 ", "name": "林德宇", "hospital": "ndmctsgh - 內湖院區", "outpatient": "感染及熱帶醫學科", "dept": "內科", "link": "NA", "time": "morning", "date": "20150812", "crawlTime": "20150729 23:19"},
{"full": "6 ", "name": "張峰義", "hospital": "ndmctsgh - 內湖院區", "outpatient": "感染及熱帶醫學科", "dept": "內科", "link": "NA", "time": "morning", "date": "20150813", "crawlTime": "20150729 23:20"},
{"full": "21 ", "name": "林永崇", "hospital": "ndmctsgh - 內湖院區", "outpatient": "感染及熱帶醫學科", "dept": "內科", "link": "NA", "time": "morning", "date": "20150813", "crawlTime": "20150729 23:20"},
{"full": "請現場掛", "name": "王甯祺", "hospital": "ndmctsgh - 內湖院區", "outpatient": "感染及熱帶醫學科", "dept": "內科", "link": "NA", "time": "morning", "date": "20150814", "crawlTime": "20150729 23:20"},
{"full": "25 ", "name": "王甯祺", "hospital": "ndmctsgh - 內湖院區", "outpatient": "感染及熱帶醫學科", "dept": "內科", "link": "NA", "time": "morning", "date": "20150817", "crawlTime": "20150729 23:20"},
{"full": "6 ", "name": "邱勝康", "hospital": "ndmctsgh - 內湖院區", "outpatient": "感染及熱帶醫學科", "dept": "內科", "link": "NA", "time": "morning", "date": "20150818", "crawlTime": "20150729 23:21"},
{"full": "7 ", "name": "葉國明", "hospital": "ndmctsgh - 內湖院區", "outpatient": "感染及熱帶醫學科", "dept": "內科", "link": "NA", "time": "afternoon", "date": "20150812", "crawlTime": "20150729 23:21"},
{"full": "21 ", "name": "林永崇", "hospital": "ndmctsgh - 內湖院區", "outpatient": "感染及熱帶醫學科", "dept": "內科", "link": "NA", "time": "afternoon", "date": "20150812", "crawlTime": "20150729 23:21"},
{"full": "6 ", "name": "葉國明", "hospital": "ndmctsgh - 內湖院區", "outpatient": "感染及熱帶醫學科", "dept": "內科", "link": "NA", "time": "afternoon", "date": "20150813", "crawlTime": "20150729 23:21"},
{"full": "休診", "name": "王甯祺", "hospital": "ndmctsgh - 內湖院區", "outpatient": "感染及熱帶醫學科", "dept": "內科", "link": "NA", "time": "afternoon", "date": "20150813", "crawlTime": "20150729 23:22"},
{"full": "6 ", "name": "楊雅頌", "hospital": "ndmctsgh - 內湖院區", "outpatient": "感染及熱帶醫學科", "dept": "內科", "link": "NA", "time": "afternoon", "date": "20150814", "crawlTime": "20150729 23:22"},
{"full": "15 ", "name": "林德宇", "hospital": "ndmctsgh - 內湖院區", "outpatient": "感染及熱帶醫學科", "dept": "內科", "link": "NA", "time": "afternoon", "date": "20150814", "crawlTime": "20150729 23:23"},
{"full": "9 ", "name": "邱勝康", "hospital": "ndmctsgh - 內湖院區", "outpatient": "感染及熱帶醫學科", "dept": "內科", "link": "NA", "time": "afternoon", "date": "20150817", "crawlTime": "20150729 23:23"},
{"full": "19 ", "name": "張峰義", "hospital": "ndmctsgh - 內湖院區", "outpatient": "感染及熱帶醫學科", "dept": "內科", "link": "NA", "time": "afternoon", "date": "20150817", "crawlTime": "20150729 23:23"},
{"full": "6 ", "name": "葉國明", "hospital": "ndmctsgh - 內湖院區", "outpatient": "感染及熱帶醫學科", "dept": "內科", "link": "NA", "time": "afternoon", "date": "20150818", "crawlTime": "20150729 23:23"},
{"full": "15 ", "name": "林德宇", "hospital": "ndmctsgh - 內湖院區", "outpatient": "感染及熱帶醫學科", "dept": "內科", "link": "NA", "time": "afternoon", "date": "20150818", "crawlTime": "20150729 23:24"},
{"full": "6 ", "name": "葉國明", "hospital": "ndmctsgh - 內湖院區", "outpatient": "感染及熱帶醫學科", "dept": "內科", "link": "NA", "time": "night", "date": "20150812", "crawlTime": "20150729 23:24"},
{"full": "9 ", "name": "林德宇", "hospital": "ndmctsgh - 內湖院區", "outpatient": "感染及熱帶醫學科", "dept": "內科", "link": "NA", "time": "morning", "date": "20150819", "crawlTime": "20150729 23:24"},
{"full": "6 ", "name": "張峰義", "hospital": "ndmctsgh - 內湖院區", "outpatient": "感染及熱帶醫學科", "dept": "內科", "link": "NA", "time": "morning", "date": "20150820", "crawlTime": "20150729 23:25"},
{"full": "24 ", "name": "林永崇", "hospital": "ndmctsgh - 內湖院區", "outpatient": "感染及熱帶醫學科", "dept": "內科", "link": "NA", "time": "morning", "date": "20150820", "crawlTime": "20150729 23:25"},
{"full": "休診", "name": "王甯祺", "hospital": "ndmctsgh - 內湖院區", "outpatient": "感染及熱帶醫學科", "dept": "內科", "link": "NA", "time": "morning", "date": "20150821", "crawlTime": "20150729 23:25"},
{"full": "23 ", "name": "王甯祺", "hospital": "ndmctsgh - 內湖院區", "outpatient": "感染及熱帶醫學科", "dept": "內科", "link": "NA", "time": "morning", "date": "20150824", "crawlTime": "20150729 23:25"},
{"full": "6 ", "name": "邱勝康", "hospital": "ndmctsgh - 內湖院區", "outpatient": "感染及熱帶醫學科", "dept": "內科", "link": "NA", "time": "morning", "date": "20150825", "crawlTime": "20150729 23:26"},
{"full": "6 ", "name": "葉國明", "hospital": "ndmctsgh - 內湖院區", "outpatient": "感染及熱帶醫學科", "dept": "內科", "link": "NA", "time": "afternoon", "date": "20150819", "crawlTime": "20150729 23:26"},
{"full": "33 ", "name": "林永崇", "hospital": "ndmctsgh - 內湖院區", "outpatient": "感染及熱帶醫學科", "dept": "內科", "link": "NA", "time": "afternoon", "date": "20150819", "crawlTime": "20150729 23:26"},
{"full": "6 ", "name": "葉國明", "hospital": "ndmctsgh - 內湖院區", "outpatient": "感染及熱帶醫學科", "dept": "內科", "link": "NA", "time": "afternoon", "date": "20150820", "crawlTime": "20150729 23:27"},
{"full": "21 ", "name": "王甯祺", "hospital": "ndmctsgh - 內湖院區", "outpatient": "感染及熱帶醫學科", "dept": "內科", "link": "NA", "time": "afternoon", "date": "20150820", "crawlTime": "20150729 23:27"},
{"full": "6 ", "name": "楊雅頌", "hospital": "ndmctsgh - 內湖院區", "outpatient": "感染及熱帶醫學科", "dept": "內科", "link": "NA", "time": "afternoon", "date": "20150821", "crawlTime": "20150729 23:27"},
{"full": "13 ", "name": "林德宇", "hospital": "ndmctsgh - 內湖院區", "outpatient": "感染及熱帶醫學科", "dept": "內科", "link": "NA", "time": "afternoon", "date": "20150821", "crawlTime": "20150729 23:27"},
{"full": "6 ", "name": "邱勝康", "hospital": "ndmctsgh - 內湖院區", "outpatient": "感染及熱帶醫學科", "dept": "內科", "link": "NA", "time": "afternoon", "date": "20150824", "crawlTime": "20150729 23:28"},
{"full": "休診", "name": "張峰義", "hospital": "ndmctsgh - 內湖院區", "outpatient": "感染及熱帶醫學科", "dept": "內科", "link": "NA", "time": "afternoon", "date": "20150824", "crawlTime": "20150729 23:28"},
{"full": "6 ", "name": "葉國明", "hospital": "ndmctsgh - 內湖院區", "outpatient": "感染及熱帶醫學科", "dept": "內科", "link": "NA", "time": "afternoon", "date": "20150825", "crawlTime": "20150729 23:28"},
{"full": "13 ", "name": "林德宇", "hospital": "ndmctsgh - 內湖院區", "outpatient": "感染及熱帶醫學科", "dept": "內科", "link": "NA", "time": "afternoon", "date": "20150825", "crawlTime": "20150729 23:28"},
{"full": "6 ", "name": "葉國明", "hospital": "ndmctsgh - 內湖院區", "outpatient": "感染及熱帶醫學科", "dept": "內科", "link": "NA", "time": "night", "date": "20150819", "crawlTime": "20150729 23:29"},
{"full": "9 ", "name": "林德宇", "hospital": "ndmctsgh - 內湖院區", "outpatient": "感染及熱帶醫學科", "dept": "內科", "link": "NA", "time": "morning", "date": "20150826", "crawlTime": "20150729 23:29"},
{"full": "休診", "name": "張峰義", "hospital": "ndmctsgh - 內湖院區", "outpatient": "感染及熱帶醫學科", "dept": "內科", "link": "NA", "time": "morning", "date": "20150827", "crawlTime": "20150729 23:29"},
{"full": "15 ", "name": "林永崇", "hospital": "ndmctsgh - 內湖院區", "outpatient": "感染及熱帶醫學科", "dept": "內科", "link": "NA", "time": "morning", "date": "20150827", "crawlTime": "20150729 23:30"},
{"full": "請現場掛", "name": "王甯祺", "hospital": "ndmctsgh - 內湖院區", "outpatient": "感染及熱帶醫學科", "dept": "內科", "link": "NA", "time": "morning", "date": "20150828", "crawlTime": "20150729 23:30"},
{"full": "6 ", "name": "葉國明", "hospital": "ndmctsgh - 內湖院區", "outpatient": "感染及熱帶醫學科", "dept": "內科", "link": "NA", "time": "afternoon", "date": "20150826", "crawlTime": "20150729 23:30"},
{"full": "11 ", "name": "林永崇", "hospital": "ndmctsgh - 內湖院區", "outpatient": "感染及熱帶醫學科", "dept": "內科", "link": "NA", "time": "afternoon", "date": "20150826", "crawlTime": "20150729 23:31"},
{"full": "6 ", "name": "葉國明", "hospital": "ndmctsgh - 內湖院區", "outpatient": "感染及熱帶醫學科", "dept": "內科", "link": "NA", "time": "afternoon", "date": "20150827", "crawlTime": "20150729 23:31"},
{"full": "11 ", "name": "王甯祺", "hospital": "ndmctsgh - 內湖院區", "outpatient": "感染及熱帶醫學科", "dept": "內科", "link": "NA", "time": "afternoon", "date": "20150827", "crawlTime": "20150729 23:31"},
{"full": "1 ", "name": "楊雅頌", "hospital": "ndmctsgh - 內湖院區", "outpatient": "感染及熱帶醫學科", "dept": "內科", "link": "NA", "time": "afternoon", "date": "20150828", "crawlTime": "20150729 23:31"},
{"full": "9 ", "name": "林德宇", "hospital": "ndmctsgh - 內湖院區", "outpatient": "感染及熱帶醫學科", "dept": "內科", "link": "NA", "time": "afternoon", "date": "20150828", "crawlTime": "20150729 23:32"},
{"full": "6 ", "name": "葉國明", "hospital": "ndmctsgh - 內湖院區", "outpatient": "感染及熱帶醫學科", "dept": "內科", "link": "NA", "time": "night", "date": "20150826", "crawlTime": "20150729 23:32"}]